influence_model/__init__.py
influence_model/influence_model.py
influence_model/learning.py
influence_model/site.py
influence_model/utils/math.py
influence_model-0.1.1.dist-info/METADATA
influence_model-0.1.1.dist-info/WHEEL
influence_model-0.1.1.dist-info/licenses/LICENSE
influence_model-0.1.1.dist-info/RECORD
