Metadata-Version: 2.1
Name: influence_model
Version: 0.1.1
Summary: A Python implementation of the influence model, a generative model that describes the interactions between networked Markov chains
Project-URL: Homepage, https://github.com/keelerh/influence-model
Project-URL: Bug Tracker, https://github.com/keelerh/influence-model/issues
Author-email: Keeley Erhardt <keeley@mit.edu>
License-File: LICENSE
Classifier: License :: OSI Approved :: MIT License
Classifier: Operating System :: OS Independent
Classifier: Programming Language :: Python :: 3
Requires-Python: >=3.7
